{
  "timestamp": "2025-09-20T05:54:35.069Z",
  "totals": {
    "count": 14,
    "errors": 0,
    "s404": 6,
    "s5xx": 4,
    "redirects": 1
  },
  "results": [
    {
      "url": "http://localhost:3000/",
      "status": 404,
      "headers": {
        "content-security-policy": "default-src 'self';style-src 'self' 'unsafe-inline';script-src 'self';img-src 'self' data: https:;connect-src 'self' wss: ws:;base-uri 'self';font-src 'self' https: data:;form-action 'self';frame-ancestors 'self';object-src 'none';script-src-attr 'none';upgrade-insecure-requests",
        "cross-origin-opener-policy": "same-origin",
        "cross-origin-resource-policy": "same-origin",
        "origin-agent-cluster": "?1",
        "referrer-policy": "no-referrer",
        "x-content-type-options": "nosniff",
        "x-dns-prefetch-control": "off",
        "x-download-options": "noopen",
        "x-frame-options": "SAMEORIGIN",
        "x-permitted-cross-domain-policies": "none",
        "x-xss-protection": "0",
        "vary": "Origin",
        "access-control-allow-credentials": "true",
        "content-type": "application/json; charset=utf-8",
        "content-length": "164",
        "etag": "W/\"a4-PK59B8vXLj+bLh5y0JpLE9SgDR4\"",
        "date": "Sat, 20 Sep 2025 05:54:34 GMT",
        "connection": "keep-alive",
        "keep-alive": "timeout=5"
      },
      "redirects": [],
      "sample": "{\"success\":false,\"error\":{\"message\":\"Route / not found\",\"statusCode\":404,\"timestamp\":\"2025-09-20T05:54:34.100Z\",\"path\":\"/\",\"method\":\"GET\",\"code\":\"ROUTE_NOT_FOUND\"}}"
    },
    {
      "url": "http://localhost:3000/api/health",
      "status": 503,
      "headers": {
        "content-security-policy": "default-src 'self';style-src 'self' 'unsafe-inline';script-src 'self';img-src 'self' data: https:;connect-src 'self' wss: ws:;base-uri 'self';font-src 'self' https: data:;form-action 'self';frame-ancestors 'self';object-src 'none';script-src-attr 'none';upgrade-insecure-requests",
        "cross-origin-opener-policy": "same-origin",
        "cross-origin-resource-policy": "same-origin",
        "origin-agent-cluster": "?1",
        "referrer-policy": "no-referrer",
        "x-content-type-options": "nosniff",
        "x-dns-prefetch-control": "off",
        "x-download-options": "noopen",
        "x-frame-options": "SAMEORIGIN",
        "x-permitted-cross-domain-policies": "none",
        "x-xss-protection": "0",
        "vary": "Origin",
        "access-control-allow-credentials": "true",
        "content-type": "application/json; charset=utf-8",
        "content-length": "293",
        "etag": "W/\"125-MyVP2VVN7OPxdVe0cBO96+FHYeU\"",
        "date": "Sat, 20 Sep 2025 05:54:34 GMT",
        "connection": "keep-alive",
        "keep-alive": "timeout=5"
      },
      "redirects": [],
      "sample": "{\"status\":\"DEGRADED\",\"timestamp\":\"2025-09-20T05:54:34.106Z\",\"environment\":\"production\",\"uptime\":25.1484909,\"memory\":{\"rss\":67645440,\"heapTotal\":25407488,\"heapUsed\":22307552,\"external\":3811707,\"arrayBuffers\":76326},\"version\":\"v22.17.0\",\"services\":{\"database\":\"unhealthy\",\"redis\":\"checking...\"}}"
    },
    {
      "url": "http://localhost:3000/api/monitoring/health",
      "status": 503,
      "headers": {
        "content-security-policy": "default-src 'self';style-src 'self' 'unsafe-inline';script-src 'self';img-src 'self' data: https:;connect-src 'self' wss: ws:;base-uri 'self';font-src 'self' https: data:;form-action 'self';frame-ancestors 'self';object-src 'none';script-src-attr 'none';upgrade-insecure-requests",
        "cross-origin-opener-policy": "same-origin",
        "cross-origin-resource-policy": "same-origin",
        "origin-agent-cluster": "?1",
        "referrer-policy": "no-referrer",
        "x-content-type-options": "nosniff",
        "x-dns-prefetch-control": "off",
        "x-download-options": "noopen",
        "x-frame-options": "SAMEORIGIN",
        "x-permitted-cross-domain-policies": "none",
        "x-xss-protection": "0",
        "vary": "Origin",
        "access-control-allow-credentials": "true",
        "content-type": "application/json; charset=utf-8",
        "content-length": "565",
        "etag": "W/\"235-W/UDg5306UExqY5JbRxMXjenNig\"",
        "date": "Sat, 20 Sep 2025 05:54:34 GMT",
        "connection": "keep-alive",
        "keep-alive": "timeout=5"
      },
      "redirects": [],
      "sample": "{\"status\":\"degraded\",\"timestamp\":\"2025-09-20T05:54:34.108Z\",\"uptime\":25.1507545,\"environment\":\"production\",\"version\":\"v22.17.0\",\"memory\":{\"used\":0,\"free\":0,\"total\":0,\"usage\":0},\"performance\":{\"totalRequests\":2,\"errorRate\":\"100.00%\",\"averageResponseTime\":\"2ms\"},\"activeAlerts\":1,\"recentErrors\":[{\"timestamp\":\"2025-09-20T05:54:34.106Z\",\"path\":\"/api/health\",\"method\":\"GET\",\"statusCode\":503,\"userAgent\":\"audit-http/1.0\",\"ip\":\"127.0.0.1\"},{\"timestamp\":\"2025-09-20T05:54:34.100Z\",\"path\":\"/\",\"method\":\"GET\",\"statusCode\":404,\"userAgent\":\"audit-http/1.0\",\"ip\":\"127.0.0.1\"}]}"
    },
    {
      "url": "http://localhost:3000/api/public",
      "status": 404,
      "headers": {
        "content-security-policy": "default-src 'self';style-src 'self' 'unsafe-inline';script-src 'self';img-src 'self' data: https:;connect-src 'self' wss: ws:;base-uri 'self';font-src 'self' https: data:;form-action 'self';frame-ancestors 'self';object-src 'none';script-src-attr 'none';upgrade-insecure-requests",
        "cross-origin-opener-policy": "same-origin",
        "cross-origin-resource-policy": "same-origin",
        "origin-agent-cluster": "?1",
        "referrer-policy": "no-referrer",
        "x-content-type-options": "nosniff",
        "x-dns-prefetch-control": "off",
        "x-download-options": "noopen",
        "x-frame-options": "SAMEORIGIN",
        "x-permitted-cross-domain-policies": "none",
        "x-xss-protection": "0",
        "vary": "Origin",
        "access-control-allow-credentials": "true",
        "content-type": "application/json; charset=utf-8",
        "content-length": "184",
        "etag": "W/\"b8-J8Q8y5zEWdKNnppewW9wkVPQN+M\"",
        "date": "Sat, 20 Sep 2025 05:54:34 GMT",
        "connection": "keep-alive",
        "keep-alive": "timeout=5"
      },
      "redirects": [],
      "sample": "{\"success\":false,\"error\":{\"message\":\"Route /api/public not found\",\"statusCode\":404,\"timestamp\":\"2025-09-20T05:54:34.111Z\",\"path\":\"/api/public\",\"method\":\"GET\",\"code\":\"ROUTE_NOT_FOUND\"}}"
    },
    {
      "url": "http://localhost:3000/admin",
      "status": 404,
      "headers": {
        "content-security-policy": "default-src 'self';style-src 'self' 'unsafe-inline';script-src 'self';img-src 'self' data: https:;connect-src 'self' wss: ws:;base-uri 'self';font-src 'self' https: data:;form-action 'self';frame-ancestors 'self';object-src 'none';script-src-attr 'none';upgrade-insecure-requests",
        "cross-origin-opener-policy": "same-origin",
        "cross-origin-resource-policy": "same-origin",
        "origin-agent-cluster": "?1",
        "referrer-policy": "no-referrer",
        "x-content-type-options": "nosniff",
        "x-dns-prefetch-control": "off",
        "x-download-options": "noopen",
        "x-frame-options": "SAMEORIGIN",
        "x-permitted-cross-domain-policies": "none",
        "x-xss-protection": "0",
        "vary": "Origin",
        "access-control-allow-credentials": "true",
        "content-type": "application/json; charset=utf-8",
        "content-length": "174",
        "etag": "W/\"ae-ZvdmsOc6HUCDuqwFpPRPNIf1Buw\"",
        "date": "Sat, 20 Sep 2025 05:54:34 GMT",
        "connection": "keep-alive",
        "keep-alive": "timeout=5"
      },
      "redirects": [],
      "sample": "{\"success\":false,\"error\":{\"message\":\"Route /admin not found\",\"statusCode\":404,\"timestamp\":\"2025-09-20T05:54:34.112Z\",\"path\":\"/admin\",\"method\":\"GET\",\"code\":\"ROUTE_NOT_FOUND\"}}"
    },
    {
      "url": "http://localhost:3000/admin",
      "status": 404,
      "headers": {
        "content-security-policy": "default-src 'self';style-src 'self' 'unsafe-inline';script-src 'self';img-src 'self' data: https:;connect-src 'self' wss: ws:;base-uri 'self';font-src 'self' https: data:;form-action 'self';frame-ancestors 'self';object-src 'none';script-src-attr 'none';upgrade-insecure-requests",
        "cross-origin-opener-policy": "same-origin",
        "cross-origin-resource-policy": "same-origin",
        "origin-agent-cluster": "?1",
        "referrer-policy": "no-referrer",
        "x-content-type-options": "nosniff",
        "x-dns-prefetch-control": "off",
        "x-download-options": "noopen",
        "x-frame-options": "SAMEORIGIN",
        "x-permitted-cross-domain-policies": "none",
        "x-xss-protection": "0",
        "vary": "Origin",
        "access-control-allow-credentials": "true",
        "content-type": "application/json; charset=utf-8",
        "content-length": "174",
        "etag": "W/\"ae-41KJPJW3mWhy8aDSduNS1osmtTU\"",
        "date": "Sat, 20 Sep 2025 05:54:34 GMT",
        "connection": "keep-alive",
        "keep-alive": "timeout=5"
      },
      "redirects": [
        {
          "status": 301,
          "location": "/admin"
        }
      ],
      "sample": "{\"success\":false,\"error\":{\"message\":\"Route /admin not found\",\"statusCode\":404,\"timestamp\":\"2025-09-20T05:54:34.116Z\",\"path\":\"/admin\",\"method\":\"GET\",\"code\":\"ROUTE_NOT_FOUND\"}}"
    },
    {
      "url": "http://localhost:3000/non-exist-123",
      "status": 404,
      "headers": {
        "content-security-policy": "default-src 'self';style-src 'self' 'unsafe-inline';script-src 'self';img-src 'self' data: https:;connect-src 'self' wss: ws:;base-uri 'self';font-src 'self' https: data:;form-action 'self';frame-ancestors 'self';object-src 'none';script-src-attr 'none';upgrade-insecure-requests",
        "cross-origin-opener-policy": "same-origin",
        "cross-origin-resource-policy": "same-origin",
        "origin-agent-cluster": "?1",
        "referrer-policy": "no-referrer",
        "x-content-type-options": "nosniff",
        "x-dns-prefetch-control": "off",
        "x-download-options": "noopen",
        "x-frame-options": "SAMEORIGIN",
        "x-permitted-cross-domain-policies": "none",
        "x-xss-protection": "0",
        "vary": "Origin",
        "access-control-allow-credentials": "true",
        "content-type": "application/json; charset=utf-8",
        "content-length": "190",
        "etag": "W/\"be-MEVeR+6YR6EXOtx3gHdXEK8Nw1g\"",
        "date": "Sat, 20 Sep 2025 05:54:34 GMT",
        "connection": "keep-alive",
        "keep-alive": "timeout=5"
      },
      "redirects": [],
      "sample": "{\"success\":false,\"error\":{\"message\":\"Route /non-exist-123 not found\",\"statusCode\":404,\"timestamp\":\"2025-09-20T05:54:34.117Z\",\"path\":\"/non-exist-123\",\"method\":\"GET\",\"code\":\"ROUTE_NOT_FOUND\"}}"
    },
    {
      "url": "http://localhost:5173/",
      "status": 200,
      "headers": {
        "access-control-allow-origin": "*",
        "content-type": "text/html",
        "cache-control": "no-cache",
        "etag": "W/\"46f1-VU9TP0ODdreiP58trdXT46prehE\"",
        "cross-origin-embedder-policy": "credentialless",
        "date": "Sat, 20 Sep 2025 05:54:34 GMT",
        "connection": "keep-alive",
        "keep-alive": "timeout=5",
        "content-length": "18161"
      },
      "redirects": [],
      "sample": "<!doctype html>\n<html lang=\"vi\">\n\t<head>\n\t\t<script type=\"module\">import { injectIntoGlobalHook } from \"/@react-refresh\";\ninjectIntoGlobalHook(window);\nwindow.$RefreshReg$ = () => {};\nwindow.$RefreshSig$ = () => (type) => type;</script>\n\n\t\t<script type=\"module\" src=\"/@vite/client\"></script>\n\n\t\t<meta charset=\"UTF-8\" />\n\t\t<link rel=\"icon\" type=\"image/svg+xml\" href=\"/vite.svg\" />\n\t\t<meta name=\"generator\" content=\"Hostinger Horizons\" />\n\t\t<meta name=\"viewport\" content=\"width=device-width, initial-scale=1.0\" />\n\t\t<meta name=\"description\" content=\"Nền tảng bình chọn trực tuyến cho cuộc thi Giọng Hát Vàng 2025. Theo dõi, bình chọn và ủng hộ thí sinh bạn yêu thích.\" />\n\t\t<title>Giọng Hát Vàng 2025</title>\n\t\t<style>\n  #root[data-edit-mode-enabled=\"true\"] [data-edit-id] {\n    cursor: pointer; \n    outline: 1px dashed #357DF9; \n    outline-offset: 2px;\n    min-height: 1em;\n  }\n  #root[data-edit-mode-enabled=\"true\"] {\n    cursor: pointer;\n  }\n  #root[data-edit-mode-enabled=\"true\"] [data-edit-id]:hover {\n    background-col"
    },
    {
      "url": "http://localhost:5173/api/health",
      "status": 503,
      "headers": {
        "access-control-allow-origin": "*",
        "content-security-policy": "default-src 'self';style-src 'self' 'unsafe-inline';script-src 'self';img-src 'self' data: https:;connect-src 'self' wss: ws:;base-uri 'self';font-src 'self' https: data:;form-action 'self';frame-ancestors 'self';object-src 'none';script-src-attr 'none';upgrade-insecure-requests",
        "cross-origin-opener-policy": "same-origin",
        "cross-origin-resource-policy": "same-origin",
        "origin-agent-cluster": "?1",
        "referrer-policy": "no-referrer",
        "x-content-type-options": "nosniff",
        "x-dns-prefetch-control": "off",
        "x-download-options": "noopen",
        "x-frame-options": "SAMEORIGIN",
        "x-permitted-cross-domain-policies": "none",
        "x-xss-protection": "0",
        "vary": "Origin",
        "access-control-allow-credentials": "true",
        "content-type": "application/json; charset=utf-8",
        "content-length": "293",
        "etag": "W/\"125-ZcCBzHVOraYsKzOOXkpmH8WdIFo\"",
        "date": "Sat, 20 Sep 2025 05:54:34 GMT",
        "connection": "close"
      },
      "redirects": [],
      "sample": "{\"status\":\"DEGRADED\",\"timestamp\":\"2025-09-20T05:54:34.149Z\",\"environment\":\"production\",\"uptime\":25.1912496,\"memory\":{\"rss\":68550656,\"heapTotal\":25931776,\"heapUsed\":23206088,\"external\":3828131,\"arrayBuffers\":92710},\"version\":\"v22.17.0\",\"services\":{\"database\":\"unhealthy\",\"redis\":\"checking...\"}}"
    },
    {
      "url": "http://localhost:5173/api/monitoring/health",
      "status": 503,
      "headers": {
        "access-control-allow-origin": "*",
        "content-security-policy": "default-src 'self';style-src 'self' 'unsafe-inline';script-src 'self';img-src 'self' data: https:;connect-src 'self' wss: ws:;base-uri 'self';font-src 'self' https: data:;form-action 'self';frame-ancestors 'self';object-src 'none';script-src-attr 'none';upgrade-insecure-requests",
        "cross-origin-opener-policy": "same-origin",
        "cross-origin-resource-policy": "same-origin",
        "origin-agent-cluster": "?1",
        "referrer-policy": "no-referrer",
        "x-content-type-options": "nosniff",
        "x-dns-prefetch-control": "off",
        "x-download-options": "noopen",
        "x-frame-options": "SAMEORIGIN",
        "x-permitted-cross-domain-policies": "none",
        "x-xss-protection": "0",
        "vary": "Origin",
        "access-control-allow-credentials": "true",
        "content-type": "application/json; charset=utf-8",
        "content-length": "988",
        "etag": "W/\"3dc-DX1sUwdn2roB8wgckgN/ApB8FU0\"",
        "date": "Sat, 20 Sep 2025 05:54:34 GMT",
        "connection": "close"
      },
      "redirects": [],
      "sample": "{\"status\":\"degraded\",\"timestamp\":\"2025-09-20T05:54:34.242Z\",\"uptime\":25.2844757,\"environment\":\"production\",\"version\":\"v22.17.0\",\"memory\":{\"used\":0,\"free\":0,\"total\":0,\"usage\":0},\"performance\":{\"totalRequests\":8,\"errorRate\":\"100.00%\",\"averageResponseTime\":\"1ms\"},\"activeAlerts\":3,\"recentErrors\":[{\"timestamp\":\"2025-09-20T05:54:34.149Z\",\"path\":\"/api/health\",\"method\":\"GET\",\"statusCode\":503,\"userAgent\":\"audit-http/1.0\",\"ip\":\"127.0.0.1\"},{\"timestamp\":\"2025-09-20T05:54:34.117Z\",\"path\":\"/non-exist-123\",\"method\":\"GET\",\"statusCode\":404,\"userAgent\":\"audit-http/1.0\",\"ip\":\"127.0.0.1\"},{\"timestamp\":\"2025-09-20T05:54:34.116Z\",\"path\":\"/admin\",\"method\":\"GET\",\"statusCode\":404,\"userAgent\":\"audit-http/1.0\",\"ip\":\"127.0.0.1\"},{\"timestamp\":\"2025-09-20T05:54:34.112Z\",\"path\":\"/admin\",\"method\":\"GET\",\"statusCode\":404,\"userAgent\":\"audit-http/1.0\",\"ip\":\"127.0.0.1\"},{\"timestamp\":\"2025-09-20T05:54:34.111Z\",\"path\":\"/api/public\",\"method\":\"GET\",\"statusCode\":404,\"userAgent\":\"audit-http/1.0\",\"ip\":\"127.0.0.1\"}]}"
    },
    {
      "url": "http://localhost:5173/api/public",
      "status": 404,
      "headers": {
        "access-control-allow-origin": "*",
        "content-security-policy": "default-src 'self';style-src 'self' 'unsafe-inline';script-src 'self';img-src 'self' data: https:;connect-src 'self' wss: ws:;base-uri 'self';font-src 'self' https: data:;form-action 'self';frame-ancestors 'self';object-src 'none';script-src-attr 'none';upgrade-insecure-requests",
        "cross-origin-opener-policy": "same-origin",
        "cross-origin-resource-policy": "same-origin",
        "origin-agent-cluster": "?1",
        "referrer-policy": "no-referrer",
        "x-content-type-options": "nosniff",
        "x-dns-prefetch-control": "off",
        "x-download-options": "noopen",
        "x-frame-options": "SAMEORIGIN",
        "x-permitted-cross-domain-policies": "none",
        "x-xss-protection": "0",
        "vary": "Origin",
        "access-control-allow-credentials": "true",
        "content-type": "application/json; charset=utf-8",
        "content-length": "184",
        "etag": "W/\"b8-+P3qW+GTIW8Gaeh2UUq6lPMAzhI\"",
        "date": "Sat, 20 Sep 2025 05:54:34 GMT",
        "connection": "close"
      },
      "redirects": [],
      "sample": "{\"success\":false,\"error\":{\"message\":\"Route /api/public not found\",\"statusCode\":404,\"timestamp\":\"2025-09-20T05:54:34.386Z\",\"path\":\"/api/public\",\"method\":\"GET\",\"code\":\"ROUTE_NOT_FOUND\"}}"
    },
    {
      "url": "http://localhost:5173/admin",
      "status": 200,
      "headers": {
        "access-control-allow-origin": "*",
        "content-type": "text/html",
        "cache-control": "no-cache",
        "etag": "W/\"46f1-VU9TP0ODdreiP58trdXT46prehE\"",
        "cross-origin-embedder-policy": "credentialless",
        "date": "Sat, 20 Sep 2025 05:54:34 GMT",
        "connection": "keep-alive",
        "keep-alive": "timeout=5",
        "content-length": "18161"
      },
      "redirects": [],
      "sample": "<!doctype html>\n<html lang=\"vi\">\n\t<head>\n\t\t<script type=\"module\">import { injectIntoGlobalHook } from \"/@react-refresh\";\ninjectIntoGlobalHook(window);\nwindow.$RefreshReg$ = () => {};\nwindow.$RefreshSig$ = () => (type) => type;</script>\n\n\t\t<script type=\"module\" src=\"/@vite/client\"></script>\n\n\t\t<meta charset=\"UTF-8\" />\n\t\t<link rel=\"icon\" type=\"image/svg+xml\" href=\"/vite.svg\" />\n\t\t<meta name=\"generator\" content=\"Hostinger Horizons\" />\n\t\t<meta name=\"viewport\" content=\"width=device-width, initial-scale=1.0\" />\n\t\t<meta name=\"description\" content=\"Nền tảng bình chọn trực tuyến cho cuộc thi Giọng Hát Vàng 2025. Theo dõi, bình chọn và ủng hộ thí sinh bạn yêu thích.\" />\n\t\t<title>Giọng Hát Vàng 2025</title>\n\t\t<style>\n  #root[data-edit-mode-enabled=\"true\"] [data-edit-id] {\n    cursor: pointer; \n    outline: 1px dashed #357DF9; \n    outline-offset: 2px;\n    min-height: 1em;\n  }\n  #root[data-edit-mode-enabled=\"true\"] {\n    cursor: pointer;\n  }\n  #root[data-edit-mode-enabled=\"true\"] [data-edit-id]:hover {\n    background-col"
    },
    {
      "url": "http://localhost:5173/admin/",
      "status": 200,
      "headers": {
        "access-control-allow-origin": "*",
        "content-type": "text/html",
        "cache-control": "no-cache",
        "etag": "W/\"46f1-VU9TP0ODdreiP58trdXT46prehE\"",
        "cross-origin-embedder-policy": "credentialless",
        "date": "Sat, 20 Sep 2025 05:54:35 GMT",
        "connection": "keep-alive",
        "keep-alive": "timeout=5",
        "content-length": "18161"
      },
      "redirects": [],
      "sample": "<!doctype html>\n<html lang=\"vi\">\n\t<head>\n\t\t<script type=\"module\">import { injectIntoGlobalHook } from \"/@react-refresh\";\ninjectIntoGlobalHook(window);\nwindow.$RefreshReg$ = () => {};\nwindow.$RefreshSig$ = () => (type) => type;</script>\n\n\t\t<script type=\"module\" src=\"/@vite/client\"></script>\n\n\t\t<meta charset=\"UTF-8\" />\n\t\t<link rel=\"icon\" type=\"image/svg+xml\" href=\"/vite.svg\" />\n\t\t<meta name=\"generator\" content=\"Hostinger Horizons\" />\n\t\t<meta name=\"viewport\" content=\"width=device-width, initial-scale=1.0\" />\n\t\t<meta name=\"description\" content=\"Nền tảng bình chọn trực tuyến cho cuộc thi Giọng Hát Vàng 2025. Theo dõi, bình chọn và ủng hộ thí sinh bạn yêu thích.\" />\n\t\t<title>Giọng Hát Vàng 2025</title>\n\t\t<style>\n  #root[data-edit-mode-enabled=\"true\"] [data-edit-id] {\n    cursor: pointer; \n    outline: 1px dashed #357DF9; \n    outline-offset: 2px;\n    min-height: 1em;\n  }\n  #root[data-edit-mode-enabled=\"true\"] {\n    cursor: pointer;\n  }\n  #root[data-edit-mode-enabled=\"true\"] [data-edit-id]:hover {\n    background-col"
    },
    {
      "url": "http://localhost:5173/non-exist-123",
      "status": 200,
      "headers": {
        "access-control-allow-origin": "*",
        "content-type": "text/html",
        "cache-control": "no-cache",
        "etag": "W/\"46f1-VU9TP0ODdreiP58trdXT46prehE\"",
        "cross-origin-embedder-policy": "credentialless",
        "date": "Sat, 20 Sep 2025 05:54:35 GMT",
        "connection": "keep-alive",
        "keep-alive": "timeout=5",
        "content-length": "18161"
      },
      "redirects": [],
      "sample": "<!doctype html>\n<html lang=\"vi\">\n\t<head>\n\t\t<script type=\"module\">import { injectIntoGlobalHook } from \"/@react-refresh\";\ninjectIntoGlobalHook(window);\nwindow.$RefreshReg$ = () => {};\nwindow.$RefreshSig$ = () => (type) => type;</script>\n\n\t\t<script type=\"module\" src=\"/@vite/client\"></script>\n\n\t\t<meta charset=\"UTF-8\" />\n\t\t<link rel=\"icon\" type=\"image/svg+xml\" href=\"/vite.svg\" />\n\t\t<meta name=\"generator\" content=\"Hostinger Horizons\" />\n\t\t<meta name=\"viewport\" content=\"width=device-width, initial-scale=1.0\" />\n\t\t<meta name=\"description\" content=\"Nền tảng bình chọn trực tuyến cho cuộc thi Giọng Hát Vàng 2025. Theo dõi, bình chọn và ủng hộ thí sinh bạn yêu thích.\" />\n\t\t<title>Giọng Hát Vàng 2025</title>\n\t\t<style>\n  #root[data-edit-mode-enabled=\"true\"] [data-edit-id] {\n    cursor: pointer; \n    outline: 1px dashed #357DF9; \n    outline-offset: 2px;\n    min-height: 1em;\n  }\n  #root[data-edit-mode-enabled=\"true\"] {\n    cursor: pointer;\n  }\n  #root[data-edit-mode-enabled=\"true\"] [data-edit-id]:hover {\n    background-col"
    }
  ]
}